factorial_aivn_pika/__init__.py
factorial_aivn_pika/app.py
factorial_aivn_pika/factorial.py
factorial_aivn_pika-0.1.0.dist-info/METADATA
factorial_aivn_pika-0.1.0.dist-info/WHEEL
factorial_aivn_pika-0.1.0.dist-info/RECORD
